cipher_xh2503/__init__.py
cipher_xh2503/cipher_xh2503.py
cipher_xh2503-0.2.0.dist-info/LICENSE
cipher_xh2503-0.2.0.dist-info/WHEEL
cipher_xh2503-0.2.0.dist-info/METADATA
cipher_xh2503-0.2.0.dist-info/RECORD
