Metadata-Version: 2.1
Name: cipher-xh2503
Version: 0.2.0
Summary: A package for doing great things!
License: MIT
Author: Xiangyu Han
Requires-Python: >=3.9.0,<4.0.0
Classifier: License :: OSI Approved :: MIT License
Classifier: Programming Language :: Python :: 3
Classifier: Programming Language :: Python :: 3.9
Requires-Dist: pandas (>=1.3.4,<2.0.0)
